tgbotbase/admin_commands.py
tgbotbase/answer.py
tgbotbase/factories.py
tgbotbase/filters.py
tgbotbase/git_issues.py
tgbotbase/github_create_issue.py
tgbotbase/global_pause.py
tgbotbase/keyboards.py
tgbotbase/middleware.py
tgbotbase/pay2paysdk.py
tgbotbase/peewee_migrator.py
tgbotbase/peewee_serializer.py
tgbotbase/query_keyboard.py
tgbotbase/renv.py
tgbotbase/uniserver.py
tgbotbase/utils.py
tgbotbase-1.1.15.dist-info/LICENSE
tgbotbase-1.1.15.dist-info/METADATA
tgbotbase-1.1.15.dist-info/WHEEL
tgbotbase-1.1.15.dist-info/top_level.txt
tgbotbase-1.1.15.dist-info/RECORD
