Metadata-Version: 2.2
Name: tgbotbase
Version: 1.1.15
Summary: Universal telegram bot base for bots maded by @abuztrade on aiogram 3.x
Home-page: https://github.com/makarworld/tgbotbase.git
Download-URL: https://github.com/makarworld/tgbotbase/archive/refs/tags/v1.1.15.zip
Author: abuztrade
Author-email: abuztrade.work@gmail.com
License: MIT License
Classifier: Development Status :: 4 - Beta
Classifier: Topic :: Communications :: Email
Classifier: Operating System :: OS Independent
Classifier: License :: OSI Approved :: MIT License
Classifier: Programming Language :: Python :: 3.10
Classifier: Intended Audience :: Developers
Classifier: Intended Audience :: Customer Service
Classifier: Intended Audience :: Financial and Insurance Industry
Requires-Python: >=3.10.0
License-File: LICENSE
Requires-Dist: aiogram
Requires-Dist: redis
Requires-Dist: peewee
Requires-Dist: ruamel.yaml
Requires-Dist: python-i18n[YAML]
Dynamic: author
Dynamic: author-email
Dynamic: classifier
Dynamic: description
Dynamic: description-content-type
Dynamic: download-url
Dynamic: home-page
Dynamic: license
Dynamic: requires-dist
Dynamic: requires-python
Dynamic: summary
